pydi_core/__init__.py
pydi_core/py.typed
pydi_core-0.1.0.dist-info/WHEEL
pydi_core-0.1.0.dist-info/METADATA
pydi_core-0.1.0.dist-info/RECORD
