Metadata-Version: 2.3
Name: pydi-core
Version: 0.1.0
Summary: A simple and lightweight dependency injection container for Python
Keywords: dependency-injection,di,ioc,container,inversion-of-control
Author: Lorenzo Brilli
License: AGPL-3.0-or-later
Classifier: Development Status :: 4 - Beta
Classifier: Intended Audience :: Developers
Classifier: License :: OSI Approved :: GNU Affero General Public License v3 or later (AGPLv3+)
Classifier: Programming Language :: Python :: 3
Classifier: Programming Language :: Python :: 3.11
Classifier: Programming Language :: Python :: 3.12
Classifier: Programming Language :: Python :: 3.13
Classifier: Topic :: Software Development :: Libraries :: Python Modules
Classifier: Typing :: Typed
Requires-Python: >=3.11
Project-URL: Homepage, https://github.com/LorenzoBrilli/PyDI
Project-URL: Issues, https://github.com/LorenzoBrilli/PyDI/issues
Project-URL: Repository, https://github.com/LorenzoBrilli/PyDI
